tablegis/__init__.py
tablegis/core.py
tablegis/tmp.wav
tablegis/utils.py
tablegis-0.0.14.dist-info/licenses/LICENSE
tablegis-0.0.14.dist-info/METADATA
tablegis-0.0.14.dist-info/WHEEL
tablegis-0.0.14.dist-info/top_level.txt
tablegis-0.0.14.dist-info/RECORD
