Metadata-Version: 2.4
Name: tablegis
Version: 0.0.14
Summary: A powerful Python library for geospatial data processing, analysis and conversion - integrating pandas with GIS operations
Author-email: Non-existent987 <jiaqi0425_000@163.com>
License: MIT License
Project-URL: Homepage, https://github.com/Non-existent987/tablegis
Project-URL: Bug Tracker, https://github.com/Non-existent987/tablegis/issues
Project-URL: Repository, https://github.com/Non-existent987/tablegis.git
Project-URL: Changelog, https://github.com/Non-existent987/tablegis/blob/main/CHANGELOG.md
Keywords: gis,tablegeo,pandas,geopandas,shapefile,Nearest,crs
Classifier: Development Status :: 4 - Beta
Classifier: Intended Audience :: Developers
Classifier: Intended Audience :: Science/Research
Classifier: Topic :: Scientific/Engineering :: GIS
Classifier: Topic :: Software Development :: Libraries :: Python Modules
Classifier: License :: OSI Approved :: MIT License
Classifier: Programming Language :: Python :: 3
Classifier: Programming Language :: Python :: 3.8
Classifier: Programming Language :: Python :: 3.9
Classifier: Programming Language :: Python :: 3.10
Classifier: Programming Language :: Python :: 3.11
Classifier: Programming Language :: Python :: 3.12
Classifier: Operating System :: OS Independent
Requires-Python: >=3.8
License-File: LICENSE
Requires-Dist: pandas
Requires-Dist: numpy
Requires-Dist: scipy
Requires-Dist: pyproj
Requires-Dist: geopandas
Requires-Dist: shapely
Provides-Extra: dev
Requires-Dist: pytest>=6.0; extra == "dev"
Requires-Dist: pytest-cov; extra == "dev"
Dynamic: license-file
